abertpy/__init__.py
abertpy/__main__.py
abertpy/args.py
abertpy/helpers.py
abertpy/models.py
abertpy/ping.py
abertpy/proxy.py
abertpy/setup.py
abertpy-0.3.1.dist-info/LICENSE
abertpy-0.3.1.dist-info/METADATA
abertpy-0.3.1.dist-info/WHEEL
abertpy-0.3.1.dist-info/entry_points.txt
abertpy-0.3.1.dist-info/RECORD
