Metadata-Version: 2.3
Name: abertpy
Version: 0.3.1
Summary: 
License: GPL3
Author: Valentin Kivachuk Burda
Author-email: vk18496@gmail.com
Requires-Python: >=3.12,<4.0
Classifier: License :: Other/Proprietary License
Classifier: Programming Language :: Python :: 3
Classifier: Programming Language :: Python :: 3.12
Classifier: Programming Language :: Python :: 3.13
Requires-Dist: aiohttp (>=3.13.1,<4.0.0)
Requires-Dist: asyncstdlib (>=3.13.1,<4.0.0)
Requires-Dist: backoff (>=2.2.1,<3.0.0)
Requires-Dist: loguru (>=0.7.3,<0.8.0)
Requires-Dist: pydantic (>=2,<3)
Requires-Dist: pydantic-typer (>=0.0.13,<0.0.14)
Requires-Dist: requests (>=2.32.5,<3.0.0)
Requires-Dist: typer (>=0.20.0,<0.21.0)
